{
  "action": "labeled",
  "issue": {
    "number": 1,
    "title": "Fix error handling in authentication system",
    "body": "When a user enters special characters in their username, the authentication system fails with a 500 error instead of properly validating and returning a user-friendly message.\n\nSteps to reproduce:\n1. Try to log in with a username containing characters like `<`, `>`, or `&`\n2. System crashes with internal server error\n\nExpected behavior: The system should sanitize inputs and return a proper validation error.",
    "labels": [
      {
        "name": "bug"
      },
      {
        "name": "AUTOFIX"
      }
    ],
    "html_url": "https://github.com/test-org/test-repo/issues/1",
    "user": {
      "login": "test-user"
    },
    "state": "open",
    "created_at": "2025-03-24T12:00:00Z",
    "updated_at": "2025-03-24T12:01:00Z"
  },
  "label": {
    "name": "AUTOFIX"
  },
  "repository": {
    "name": "test-repo",
    "owner": {
      "login": "test-org"
    },
    "html_url": "https://github.com/test-org/test-repo"
  }
}